pastpy/__init__.py
pastpy/__main__.py
pastpy/cli.py
pastpy/database/__init__.py
pastpy/database/database.py
pastpy/database/database_image.py
pastpy/database/database_object.py
pastpy/database/impl/__init__.py
pastpy/database/impl/dbf/__init__.py
pastpy/database/impl/dbf/_dbf_table.py
pastpy/database/impl/dbf/dbf_database.py
pastpy/database/impl/dbf/dbf_database_image.py
pastpy/database/impl/dbf/dbf_database_object.py
pastpy/database/impl/dbf/objects_dbf_table.py
pastpy/database/impl/dummy/__init__.py
pastpy/database/impl/dummy/dummy_database.py
pastpy/database/impl/dummy/dummy_database_image.py
pastpy/database/impl/dummy/dummy_database_object.py
pastpy/database/impl/online/__init__.py
pastpy/database/impl/online/online_database.py
pastpy/database/impl/online/online_database_image.py
pastpy/database/impl/online/online_database_object.py
pastpy/database/impl/online/online_database_object_detail_html_parser.py
pastpy/database/impl/online/online_database_objects_list_html_parser.py
pastpy/database/impl/online/online_file_downloader.py
pastpy/database/impl/online/online_file_paths.py
pastpy/gen/__init__.py
pastpy/gen/non_blank_string.py
pastpy/gen/database/__init__.py
pastpy/gen/database/database_configuration.py
pastpy/gen/database/impl/__init__.py
pastpy/gen/database/impl/dbf/__init__.py
pastpy/gen/database/impl/dbf/dbf_database_configuration.py
pastpy/gen/database/impl/dbf/objects_dbf_record.py
pastpy/gen/database/impl/dummy/__init__.py
pastpy/gen/database/impl/dummy/dummy_database_configuration.py
pastpy/gen/database/impl/online/__init__.py
pastpy/gen/database/impl/online/online_database_configuration.py
pastpy/gen/database/impl/online/online_database_object_detail.py
pastpy/gen/database/impl/online/online_database_object_detail_image.py
pastpy/gen/database/impl/online/online_database_object_detail_image_type.py
pastpy/gen/database/impl/online/online_database_objects_list_item.py
pastpy-1.0.3.dist-info/METADATA
pastpy-1.0.3.dist-info/WHEEL
pastpy-1.0.3.dist-info/entry_points.txt
pastpy-1.0.3.dist-info/top_level.txt
pastpy-1.0.3.dist-info/RECORD
